[
  {
    "key": "Item-Case 4-16-Lockdown System-displayName",
    "original": "Lockdown System",
    "translation": "Система изоляции",
    "stage": 1,
    "context": "{\n  \"Name\": \"Lockdown System\",\n  \"Idx\": 16,\n  \"Attr\": \"displayName\"\n}"
  },
  {
    "key": "Item-Case 4-16-Lockdown System-description",
    "original": "The lockdown system covers the entire manor. Once activated, it creates magical barriers that prevent anyone from leaving or teleporting out of the building. In addition to this, it covers the entire manor in an <b>Anti-Magic Field</b>. Within this field, any and all magical effects are nullified and disabled.\r\\n\r\\nHowever, anyone physically or magically connected to the Sword of Spell Eating would be immune to the effects of the <b>Anti-Magic Fields</b>.\r",
    "translation": "Система изоляции покрывает целое поместье. При активации, она создаёт магические барьеры, которые не позволяют кому-либо выйти или телепортировать из здания. В добавок, оно создаёт <b>Анти-Магическое Поле</b>. Это поле обнуляет любые магические эффекты.\\n\\nОднако, любой, кто имеет физический или магический контакт с Мечом-Поглотителем Заклятий, имеет полный иммунитет к <b>Анти-Магическим Полям</b>.",
    "stage": 1,
    "context": "{\n  \"Name\": \"Lockdown System\",\n  \"Idx\": 16,\n  \"Attr\": \"description\"\n}"
  }
]