[
  {
    "key": "Item-Case 4-8-Sword of Spell Eating 3-displayName",
    "original": "Sword of Spell Eating",
    "translation": "Меч-Поглотитель Заклятий",
    "stage": 1,
    "context": "{\n  \"Name\": \"Sword of Spell Eating 3\",\n  \"Idx\": 8,\n  \"Attr\": \"displayName\"\n}"
  },
  {
    "key": "Item-Case 4-8-Sword of Spell Eating 3-description",
    "original": "The Sword of Spell Eating is an ancient artifact. When wielded by a creature, that creature and anything connected to them (physically or magically) are immune to all harmful magical effects. Legends say that it was forged through a Blood Contract between a mage and a demon.\r\\n\r\\nOn the night of the murder, someone used a powerful spell to completely shatter the magically protected glass that was containing it. It was later found in Beatrice Frega's old room.\r",
    "translation": "Меч-Поглотитель Заклятий это древний артефакт. Когда им владеет существо, оно и всё, что с ним связано (физически или магически), получают иммунитет ко всей вредоносной магии. Легенды гласят, что этот меч был выкован на основе Кровавого Контракт между магом и демоном./n/nВ ночь убийства, кто-то использовал могущественное заклинание и полностью раздробил магически защищённое стекло витрины. Он был украден в ночь убийства и был найден в старой комнате Беатрис Фреги.",
    "stage": 1,
    "context": "{\n  \"Name\": \"Sword of Spell Eating 3\",\n  \"Idx\": 8,\n  \"Attr\": \"description\"\n}"
  }
]