[
  {
    "key": "Item-Case 2-13-Jan's Statement-displayName",
    "original": "Jan's Statement",
    "translation": "Показания Яна",
    "stage": 5,
    "context": "{\n  \"Name\": \"Jan's Statement\",\n  \"Idx\": 13,\n  \"Attr\": \"displayName\"\n}"
  },
  {
    "key": "Item-Case 2-13-Jan's Statement-description",
    "original": "Thirty minutes before the Ianus twins found the body, Bellwether walked past Jan in the west wing hallway. He was in her path, so she shoved him out of her way. After that, she knocked over a vase and shattered it. Even though Jan didn’t say anything to her, she yelled at him to “Be quiet!”. After this interaction, she walked into Lecture Hall 2-B.",
    "translation": "За 30 минут до обнаружения тела, Беллвезер прошла мимо Яна в коридоре западного крыла. Он был на её пути, а потому от оттолкнула его. После этого, она опрокинула вазу и разбила её. Даже с учетом, что Ян не сказал ни слова, она прокричала \"Тишина!\". После возгласа, она направилась в Лекторию 2-Б.",
    "stage": 5,
    "context": "{\n  \"Name\": \"Jan's Statement\",\n  \"Idx\": 13,\n  \"Attr\": \"description\"\n}"
  }
]