[
  {
    "key": "Item-Case 2-15-Bellwether's Plan 2-displayName",
    "original": "Bellwether's Plan",
    "translation": "Плен Беллвезер",
    "stage": 5,
    "context": "{\n  \"Name\": \"Bellwether's Plan 2\",\n  \"Idx\": 15,\n  \"Attr\": \"displayName\"\n}"
  },
  {
    "key": "Item-Case 2-15-Bellwether's Plan 2-description",
    "original": "House Frega was planning to fire Headmaster Theodore Redmond and replace him with Catherine Bellwether. They were also planning to fire all of the academy staff and replace them with Arcane Constructs.\r\\n\r\\nThis was supposed to be kept a secret. But according to Jan, Bellwether revealed this plan to the headmaster during a meeting a “few weeks ago”.\r",
    "translation": "Дом Фрега планировал уволить Директора Теодора Редмонда и заменить его на Кэтрин Беллвезер. Они также планировали уволить весь персонал академии и заменить их Конструктами Аркан.\\n\\nЭто предполагалось остаться в тайне. Но согласно Яну, Беллвезер рассказал свой план директору на встрече \"несколько недель назад\".",
    "stage": 5,
    "context": "{\n  \"Name\": \"Bellwether's Plan 2\",\n  \"Idx\": 15,\n  \"Attr\": \"description\"\n}"
  }
]