{
  "m_GameObject": {
    "m_FileID": 0,
    "m_PathID": 5116
  },
  "m_Enabled": 1,
  "m_Script": {
    "m_FileID": 1,
    "m_PathID": 907
  },
  "m_Name": "",
  "inputName": "Меню Записей",
  "inputRef": "Open Notes",
  "isKeyboard": 0,
  "labelText": {
    "m_FileID": 0,
    "m_PathID": 14089
  },
  "inputValue": {
    "m_FileID": 0,
    "m_PathID": 14042
  },
  "altInputValue": {
    "m_FileID": 0,
    "m_PathID": 18096
  },
  "inputButton": {
    "m_FileID": 0,
    "m_PathID": 13789
  },
  "altInputButton": {
    "m_FileID": 0,
    "m_PathID": 13994
  },
  "allowLeftClick": 0
}