[
  {
    "key": "SpellLibrary-4-Frost Wave-displayName",
    "original": "Frost Wave",
    "translation": "Ледяная Волна",
    "stage": 5,
    "context": "{\n  \"Name\": \"Frost Wave\",\n  \"Idx\": 4,\n  \"Attr\": \"displayName\"\n}"
  },
  {
    "key": "SpellLibrary-4-Frost Wave-description",
    "original": "Anything caught within range is hit with a blast of extremely cold air. Liquids hit will be immediately frozen and organic life will immediately enter stages of hypothermia.",
    "translation": "Всё, что находиться в радиусе досягаемости, обдувается экстремально холодным воздухом. Жидкости во мгновение застывают, а органическая жизнь незамедлительно переходить в состояние гипотермии.",
    "stage": 5,
    "context": "{\n  \"Name\": \"Frost Wave\",\n  \"Idx\": 4,\n  \"Attr\": \"description\"\n}"
  },
  {
    "key": "SpellLibrary-4-Frost Wave-incantation",
    "original": "None",
    "translation": "Нет",
    "stage": 5,
    "context": "{\n  \"Name\": \"Frost Wave\",\n  \"Idx\": 4,\n  \"Attr\": \"incantation\"\n}"
  },
  {
    "key": "SpellLibrary-4-Frost Wave-gesture",
    "original": "Outstretch both hands",
    "translation": "Вытянуть обе руки",
    "stage": 5,
    "context": "{\n  \"Name\": \"Frost Wave\",\n  \"Idx\": 4,\n  \"Attr\": \"gesture\"\n}"
  },
  {
    "key": "SpellLibrary-4-Frost Wave-duration",
    "original": "Instant",
    "translation": "Мгновенная",
    "stage": 5,
    "context": "{\n  \"Name\": \"Frost Wave\",\n  \"Idx\": 4,\n  \"Attr\": \"duration\"\n}"
  }
]