[
  {
    "key": "Stefanic Dracogen-displayName",
    "original": "Stefanic Dracogen",
    "translation": "Стефаник Дракоген",
    "stage": 5,
    "context": "{\n  \"Name\": \"Stefanic Dracogen\",\n  \"Attr\": \"displayName\"\n}"
  },
  {
    "key": "Stefanic Dracogen-description",
    "original": "",
    "translation": "",
    "stage": -1,
    "context": "{\n  \"Name\": \"Stefanic Dracogen\",\n  \"Attr\": \"description\"\n}"
  },
  {
    "key": "Stefanic Dracogen-occupation",
    "original": "Guildmaster",
    "translation": "Гильдмастер",
    "stage": 1,
    "context": "{\n  \"Name\": \"Stefanic Dracogen\",\n  \"Attr\": \"occupation\"\n}"
  },
  {
    "key": "Stefanic Dracogen-arcaneArt",
    "original": "None",
    "translation": "Нет",
    "stage": 5,
    "context": "{\n  \"Name\": \"Stefanic Dracogen\",\n  \"Attr\": \"arcaneArt\"\n}"
  }
]