[
  {
    "key": "Valerie Ianus-displayName",
    "original": "Valerie Ianus",
    "translation": "瓦莱丽·伊努斯",
    "stage": 1,
    "context": "{\n  \"Name\": \"Valerie Ianus\",\n  \"Attr\": \"displayName\"\n}"
  },
  {
    "key": "Valerie Ianus-description",
    "original": "A member of the kitchen staff at the Imperial Academy. She’s an identical twin to her sister Valentina. They both physically look the same.",
    "translation": "帝国学院厨房的工作人员之一。瓦伦蒂娜的同胞姐妹，看起来一模一样。",
    "stage": 1,
    "context": "{\n  \"Name\": \"Valerie Ianus\",\n  \"Attr\": \"description\"\n}"
  },
  {
    "key": "Valerie Ianus-occupation",
    "original": "Kitchen Staff",
    "translation": "厨房工作人员",
    "stage": 1,
    "context": "{\n  \"Name\": \"Valerie Ianus\",\n  \"Attr\": \"occupation\"\n}"
  },
  {
    "key": "Valerie Ianus-altDescriptions-0",
    "original": "A member of the kitchen staff at the Imperial Academy. She’s an identical twin to her sister Valentina. They both physically look the same.\\n\\nShe's secretly been hiding the fact that she's a mage. This is illegal under the laws of Wyverngarde.",
    "translation": "帝国学院厨房的工作人员之一。瓦伦蒂娜的同胞姐妹，看起来一模一样。\\n\\n隐藏了自己其实是法师的事。这一点违反维文加德法律。",
    "stage": 1,
    "context": "{\n  \"Name\": \"Valerie Ianus\",\n  \"Attr\": \"altDescriptions\",\n  \"idx\": 0\n}"
  },
  {
    "key": "Valerie Ianus-arcaneArt",
    "original": "None",
    "translation": "无",
    "stage": 1,
    "context": "{\n  \"Name\": \"Valerie Ianus\",\n  \"Attr\": \"arcaneArt\"\n}"
  }
]