[
  {
    "key": "Item-Case 1-5-Celeste's Spell Compendium-displayName",
    "original": "Celeste's Spell Compendium",
    "translation": null,
    "context": "{\n  \"Name\": \"Celeste's Spell Compendium\",\n  \"Idx\": 5,\n  \"Attr\": \"displayName\"\n}"
  },
  {
    "key": "Item-Case 1-5-Celeste's Spell Compendium-description",
    "original": "It’s Celeste McCoy’s Spell Compendium. It contains the formula for the following spell: Mage Blade.",
    "translation": null,
    "context": "{\n  \"Name\": \"Celeste's Spell Compendium\",\n  \"Idx\": 5,\n  \"Attr\": \"description\"\n}"
  }
]